<annotation>
	<folder></folder>
	<filename>package_1_jpg.rf.bf54f19196391455db1b0f3f39617b53.jpg</filename>
	<path>package_1_jpg.rf.bf54f19196391455db1b0f3f39617b53.jpg</path>
	<source>
		<database>roboflow.ai</database>
	</source>
	<size>
		<width>3024</width>
		<height>4032</height>
		<depth>3</depth>
	</size>
	<segmented>0</segmented>
	<object>
		<name>package</name>
		<pose>Unspecified</pose>
		<truncated>0</truncated>
		<difficult>0</difficult>
		<occluded>0</occluded>
		<bndbox>
			<xmin>1603</xmin>
			<xmax>2003</xmax>
			<ymin>1932</ymin>
			<ymax>2866</ymax>
		</bndbox>
	</object>
	<object>
		<name>package</name>
		<pose>Unspecified</pose>
		<truncated>0</truncated>
		<difficult>0</difficult>
		<occluded>0</occluded>
		<bndbox>
			<xmin>636</xmin>
			<xmax>1915</xmax>
			<ymin>1427</ymin>
			<ymax>2749</ymax>
		</bndbox>
	</object>
</annotation>
